flask_kvsession/__init__.py
Flask_KVSession_fork-0.6.4.dist-info/LICENSE
Flask_KVSession_fork-0.6.4.dist-info/METADATA
Flask_KVSession_fork-0.6.4.dist-info/WHEEL
Flask_KVSession_fork-0.6.4.dist-info/top_level.txt
Flask_KVSession_fork-0.6.4.dist-info/RECORD
