Metadata-Version: 2.1
Name: Flask-KVSession-fork
Version: 0.6.4
Summary: Transparent server-side session support for flask
Home-page: https://github.com/infobyte/flask-kvsession
Author: Marc Brinkmann
Author-email: git@marcbrinkmann.de
License: MIT
Platform: any
Classifier: Programming Language :: Python :: 2
Classifier: Programming Language :: Python :: 3
License-File: LICENSE
Requires-Dist: Flask (>=0.8)
Requires-Dist: simplekv (>=0.9.2)
Requires-Dist: werkzeug
Requires-Dist: itsdangerous (>=0.20)
Requires-Dist: six
